hawkroutines.cpython-310-x86_64-linux-gnu.so
vbfcprw-0.2.dist-info/RECORD
vbfcprw-0.2.dist-info/METADATA
vbfcprw-0.2.dist-info/LICENSE
vbfcprw-0.2.dist-info/top_level.txt
vbfcprw-0.2.dist-info/WHEEL
vbfcprw.libs/libquadmath-96973f99.so.0.0.0
vbfcprw.libs/libgfortran-040039e1.so.5.0.0
vbfcprw.libs/libz-745e0a09.so.1.2.7
vbfcprw/vbfcprw.py
vbfcprw/constants.py
vbfcprw/test_vbfcprw.py
vbfcprw/test.py
vbfcprw/__init__.py
vbfcprw/pdf.py
vbfcprw/data/CT10/CT10_0000.dat
vbfcprw/data/CT10/CT10.info
