Metadata-Version: 2.1
Name: vbfcprw
Version: 0.2
Summary: wrapper for simplified CP reweighting using HAWK generator
Home-page: https://github.com/dhohn/vbfcprw
Author: David Hohn
Author-email: hohn.david@gmail.com
License: MIT
Platform: UNKNOWN
Classifier: Intended Audience :: Science/Research
Classifier: License :: OSI Approved :: MIT License
Classifier: Programming Language :: Fortran
Classifier: Topic :: Scientific/Engineering :: Physics
License-File: LICENSE
